hil_general_test/__init__.py
hil_general_test/case_help/__init__.py
hil_general_test/case_help/case_Logger.py
hil_general_test/case_help/case_configParser.py
hil_general_test/case_help/case_configWrite.py
hil_general_test/case_help/case_dataBase.py
hil_general_test/case_help/case_data_prepare.py
hil_general_test/case_help/case_execute_prepare.py
hil_general_test/case_help/case_getMappingFile.py
hil_general_test/case_help/case_jsonParser.py
hil_general_test/case_help/case_pro_prepare.py
hil_general_test/case_help/case_step.py
hil_general_test/case_main/__init__.py
hil_general_test/case_main/conftest.py
hil_general_test/case_main/hil_general_test.py
hil_general_test-1.0.719.dist-info/LICENSE
hil_general_test-1.0.719.dist-info/METADATA
hil_general_test-1.0.719.dist-info/WHEEL
hil_general_test-1.0.719.dist-info/top_level.txt
hil_general_test-1.0.719.dist-info/RECORD
