Metadata-Version: 2.1
Name: hil-general-test
Version: 1.0.719
Summary: vcarhilclient
Home-page: 
Author: hil
Author-email: service@vcarsystem.com
Classifier: Programming Language :: Python :: 3
Classifier: License :: OSI Approved :: MIT License
Classifier: Operating System :: OS Independent
Requires-Python: >=3.6
License-File: LICENSE
Requires-Dist: vcarhilclient
Requires-Dist: pytest
Requires-Dist: allure-pytest
Requires-Dist: PyMySQL
